code_video/__init__.py
code_video/autoscale.py
code_video/code_walkthrough.py
code_video/comment_parser.py
code_video/layout.py
code_video/music.py
code_video/player.py
code_video/scene.py
code_video/sequence.py
code_video/widgets.py
code_video_cli/__init__.py
code_video_generator-0.5.0.dist-info/LICENSE
code_video_generator-0.5.0.dist-info/METADATA
code_video_generator-0.5.0.dist-info/WHEEL
code_video_generator-0.5.0.dist-info/entry_points.txt
code_video_generator-0.5.0.dist-info/top_level.txt
code_video_generator-0.5.0.dist-info/RECORD
